_scandir.cp36-win32.pyd
scandir.py
scandir-1.8.dist-info/METADATA
scandir-1.8.dist-info/RECORD
scandir-1.8.dist-info/WHEEL
scandir-1.8.dist-info/top_level.txt
